<Document id="0000056" source="ADAM" url="https://www.nlm.nih.gov/medlineplus/ency/article/007208.htm">
 
<Focus>ACL reconstruction</Focus>
<FocusAnnotations>
	<Category>Other</Category>
	<Synonyms>
		<Synonym>Anterior cruciate ligament repair</Synonym>
	</Synonyms>
</FocusAnnotations>
<QAPairs>
	<QAPair pid="1">
			<Question qid="0000056-1" qtype="information">Do you have information about ACL reconstruction</Question>
			<Answer>ACL reconstruction is surgery to reconstruct the ligament in the center of your knee. The anterior cruciate ligament (ACL) connects your shin bone (tibia) to your thigh bone (femur). A tear of this ligament can cause your knee to give way during physical activity, most often during side-step or crossover movements.</Answer>
	</QAPair>
</QAPairs>
</Document>